collect_unexported/__init__.py
collect_unexported/__main__.py
collect_unexported/collect-unexported.1
collect_unexported/defs.py
collect_unexported/examine.py
collect_unexported/gitrepo.py
collect_unexported/parse.py
collect_unexported/py.typed
collect_unexported-0.1.1.dist-info/METADATA
collect_unexported-0.1.1.dist-info/WHEEL
collect_unexported-0.1.1.dist-info/entry_points.txt
collect_unexported-0.1.1.dist-info/RECORD
